py_ms_cognitive/__init__.py
py_ms_cognitive/py_ms_cognitive_search/__init__.py
py_ms_cognitive/py_ms_cognitive_search/py_ms_cognitive_image_search.py
py_ms_cognitive/py_ms_cognitive_search/py_ms_cognitive_news_search.py
py_ms_cognitive/py_ms_cognitive_search/py_ms_cognitive_search.py
py_ms_cognitive/py_ms_cognitive_search/py_ms_cognitive_suggestions.py
py_ms_cognitive/py_ms_cognitive_search/py_ms_cognitive_video_search.py
py_ms_cognitive/py_ms_cognitive_search/py_ms_cognitive_web_search.py
py_ms_cognitive-0.4.0.dist-info/DESCRIPTION.rst
py_ms_cognitive-0.4.0.dist-info/LICENSE.txt
py_ms_cognitive-0.4.0.dist-info/METADATA
py_ms_cognitive-0.4.0.dist-info/RECORD
py_ms_cognitive-0.4.0.dist-info/WHEEL
py_ms_cognitive-0.4.0.dist-info/metadata.json
py_ms_cognitive-0.4.0.dist-info/top_level.txt
tests/__init__.py
tests/test_py_ms_cognitive.py
