Metadata-Version: 2.0
Name: py-ms-cognitive
Version: 0.4.0
Summary: A simple lightweight python wrapper for the Microsoft Cognitive Services.
Home-page: https://github.com/tristantao/py-ms-cognitive
Author: Tristan Tao
Author-email: tristan@teamleada.com
License: MIT
Keywords: Microsoft,Cognitive Services,API,Search
Platform: UNKNOWN
Classifier: Development Status :: 2 - Pre-Alpha
Classifier: Intended Audience :: Developers
Classifier: License :: OSI Approved :: MIT License
Classifier: Operating System :: OS Independent
Classifier: Programming Language :: Python
Classifier: Programming Language :: Python :: 2
Classifier: Programming Language :: Python :: 3
Classifier: Topic :: Software Development :: Libraries :: Python Modules
Requires-Dist: requests
